cm2utils/ExternFileParams.py
cm2utils/Utils.py
cm2utils/VtkGenerator.py
cm2utils/__init__.py
cm2utils-0.0.4.dist-info/METADATA
cm2utils-0.0.4.dist-info/WHEEL
cm2utils-0.0.4.dist-info/top_level.txt
cm2utils-0.0.4.dist-info/RECORD
